datatoys/__init__.py
datatoys-0.1.1.dist-info/WHEEL
datatoys-0.1.1.dist-info/METADATA
datatoys-0.1.1.dist-info/RECORD
